colourgan/__init__.py
colourgan/config.py
colourgan/data.py
colourgan/logger.py
colourgan/model.py
colourgan/networks.py
colourgan/streamlit.py
colourgan/utils.py
colourgan-1.0.3.dist-info/LICENSE
colourgan-1.0.3.dist-info/METADATA
colourgan-1.0.3.dist-info/WHEEL
colourgan-1.0.3.dist-info/top_level.txt
colourgan-1.0.3.dist-info/RECORD
