Metadata-Version: 2.1
Name: colourgan
Version: 1.0.3
Summary: GAN Based colouring model
Home-page: https://github.com/narenderkumarnain/GAN-Apps
Author: Narender Nain
Author-email: narenderkumarnain@gmail.com
License: UNKNOWN
Platform: UNKNOWN
Classifier: Programming Language :: Python :: 3
Classifier: License :: OSI Approved :: MIT License
Classifier: Operating System :: OS Independent
Requires-Python: >=3.6
License-File: LICENSE
Requires-Dist: numpy
Requires-Dist: opencv-python (==4.5.2.52)
Requires-Dist: Pillow (==8.2.0)
Requires-Dist: torch (==1.8.1)
Requires-Dist: torchvision (==0.9.1)
